LICENSE
README.md
setup.py
benchmarks/__init__.py
benchmarks/benchmarks.py
grandiso/__init__.py
grandiso/queues.py
grandiso/test_grandiso.py
grandiso/test_queues.py
grandiso.egg-info/PKG-INFO
grandiso.egg-info/SOURCES.txt
grandiso.egg-info/dependency_links.txt
grandiso.egg-info/requires.txt
grandiso.egg-info/top_level.txt