Metadata-Version: 2.1
Name: grandiso
Version: 2.2.0
Summary: Performant subgraph isomorphism
Home-page: https://github.com/aplbrain/grandiso-networkx
Author: Jordan Matelsky
Author-email: opensource@matelsky.com
Classifier: Programming Language :: Python :: 3
Classifier: License :: OSI Approved :: MIT License
Classifier: Operating System :: OS Independent
License-File: LICENSE
